src/__init__.py
src/__init__.pyi
src/main.py
src/main.pyi
src/almanak_library/__init__.py
src/almanak_library/__init__.pyi
src/almanak_library/constants.py
src/almanak_library/constants.pyi
src/almanak_library/custom_exceptions.py
src/almanak_library/custom_exceptions.pyi
src/almanak_library/enums.py
src/almanak_library/enums.pyi
src/almanak_library/init_sdk.py
src/almanak_library/init_sdk.pyi
src/almanak_library/sdk_registry.py
src/almanak_library/sdk_registry.pyi
src/almanak_library/metrics/__init__.py
src/almanak_library/metrics/__init__.pyi
src/almanak_library/metrics/engine.py
src/almanak_library/metrics/engine.pyi
src/almanak_library/metrics/metrics_actions.py
src/almanak_library/metrics/metrics_actions.pyi
src/almanak_library/metrics/metrics_agg.py
src/almanak_library/metrics/metrics_agg.pyi
src/almanak_library/metrics/metrics_logger.py
src/almanak_library/metrics/metrics_logger.pyi
src/almanak_library/models/__init__.py
src/almanak_library/models/__init__.pyi
src/almanak_library/models/action.py
src/almanak_library/models/action.pyi
src/almanak_library/models/action_bundle.py
src/almanak_library/models/action_bundle.pyi
src/almanak_library/models/params.py
src/almanak_library/models/params.pyi
src/almanak_library/models/receipt.py
src/almanak_library/models/receipt.pyi
src/almanak_library/models/sdk.py
src/almanak_library/models/sdk.pyi
src/almanak_library/models/transaction.py
src/almanak_library/models/transaction.pyi
src/almanak_library/profiler/time_block.py
src/almanak_library/profiler/time_block.pyi
src/almanak_library/profiler/utils.py
src/almanak_library/profiler/utils.pyi
src/almanak_library/receipt_parser/__init__.py
src/almanak_library/receipt_parser/__init__.pyi
src/almanak_library/receipt_parser/enso_receipt.py
src/almanak_library/receipt_parser/enso_receipt.pyi
src/almanak_library/receipt_parser/i_receipt_parser.py
src/almanak_library/receipt_parser/i_receipt_parser.pyi
src/almanak_library/receipt_parser/receipt_parser_manager.py
almanak_src-0.0.11.dist-info/METADATA
almanak_src-0.0.11.dist-info/WHEEL
almanak_src-0.0.11.dist-info/top_level.txt
almanak_src-0.0.11.dist-info/RECORD
